SNTOTPConverter/SNTOTPConverter.py
SNTOTPConverter/__init__.py
SNTOTPConverter/__main__.py
sntotpconverter-1.1.1.dist-info/licenses/LICENSE
sntotpconverter-1.1.1.dist-info/METADATA
sntotpconverter-1.1.1.dist-info/WHEEL
sntotpconverter-1.1.1.dist-info/entry_points.txt
sntotpconverter-1.1.1.dist-info/top_level.txt
sntotpconverter-1.1.1.dist-info/RECORD
