Metadata-Version: 2.4
Name: SNTOTPConverter
Version: 1.1.1
Summary: Script for importing/exporting TOTP 2-factor authentication codes for Standard Notes.
Author: LittleBit
Author-email: littlebit@littlebitstudios.com
License: MIT
Classifier: License :: OSI Approved :: MIT License
Classifier: Operating System :: OS Independent
License-File: LICENSE
Dynamic: author
Dynamic: author-email
Dynamic: classifier
Dynamic: description
Dynamic: description-content-type
Dynamic: license
Dynamic: license-file
Dynamic: summary
